moctl/moctl.py
moname/moname.py
moera_tools-0.5.0.dist-info/LICENSE
moera_tools-0.5.0.dist-info/METADATA
moera_tools-0.5.0.dist-info/WHEEL
moera_tools-0.5.0.dist-info/entry_points.txt
moera_tools-0.5.0.dist-info/top_level.txt
moera_tools-0.5.0.dist-info/RECORD
